Metadata-Version: 2.1
Name: python-lzrw1-kh
Version: 0.1
Summary: A pure Python implementation of LZRW1/KH compression algorithm
Home-page: http://github.com/nmantani/python-lzrw1-kh
Author: Nobutaka Mantani
Author-email: nobutaka@nobutaka.org
License: BSD 2-clause
Platform: UNKNOWN
License-File: LICENSE.txt
